{
  "entrypoints": [
    "main"
  ],
  "origins": {
    "2529": [
      532,
      3089,
      4368,
      6103,
      8610,
      2529
    ],
    "4368": [
      532,
      2529,
      3085,
      3089,
      6103,
      7918,
      8610,
      4368
    ],
    "4972": [
      4972
    ],
    "17896441": [
      532,
      4368,
      7918
    ],
    "97580723": [
      9053
    ],
    "main": [
      532,
      1303,
      179
    ],
    "runtime~main": [
      179,
      532,
      1303
    ],
    "01a85c17": [
      532,
      4013
    ],
    "01ec86e8": [
      75
    ],
    "0a6dc3e9": [
      5522
    ],
    "0fdf012f": [
      7412
    ],
    "0fec271b": [
      6743
    ],
    "10f8c402": [
      532,
      3208
    ],
    "1203df09": [
      6476
    ],
    "14eb3368": [
      532,
      9817
    ],
    "15b074d4": [
      532,
      4287
    ],
    "177d2f1b": [
      9035
    ],
    "1a118389": [
      5958
    ],
    "1be78505": [
      532,
      4972
    ],
    "1df93b7f": [
      532,
      3237
    ],
    "1f391b9e": [
      532,
      4368,
      3085
    ],
    "217d5635": [
      2486
    ],
    "2af48450": [
      4605
    ],
    "2b66f623": [
      532,
      1108
    ],
    "3400adb2": [
      532,
      545
    ],
    "34b7720e": [
      9883
    ],
    "35d10f69": [
      532,
      7361
    ],
    "3720c009": [
      532,
      3751
    ],
    "393be207": [
      7414
    ],
    "3ae4ab60": [
      532,
      3629
    ],
    "3fdb0b01": [
      7773
    ],
    "55960ee5": [
      4121
    ],
    "60c9bd7f": [
      6214
    ],
    "6875c492": [
      532,
      2529,
      4368,
      8610
    ],
    "69afaff5": [
      532,
      1290
    ],
    "6bfbe0c6": [
      532,
      7418
    ],
    "7d087b07": [
      532,
      97
    ],
    "814f3328": [
      2535
    ],
    "86ccd6d1": [
      6737
    ],
    "878483fc": [
      1811
    ],
    "8d8aa384": [
      3390
    ],
    "8fd214de": [
      532,
      8493
    ],
    "92caa433": [
      8913
    ],
    "92d963c9": [
      2633
    ],
    "935f2afb": [
      53
    ],
    "96082b4e": [
      7867
    ],
    "961b356e": [
      5942
    ],
    "9e4087bc": [
      3608
    ],
    "a08e0254": [
      9913
    ],
    "a6aa9e1f": [
      532,
      2529,
      4368,
      3089
    ],
    "a7ce38cf": [
      2085
    ],
    "a7e3f0b1": [
      3170
    ],
    "a910c3a6": [
      6611
    ],
    "b53f932d": [
      9971
    ],
    "b797b19a": [
      884
    ],
    "ccc49370": [
      532,
      2529,
      4368,
      6103
    ],
    "cd1338b3": [
      6828
    ],
    "d9d034db": [
      167
    ],
    "df203c0f": [
      9924
    ],
    "e0032ae8": [
      1094
    ],
    "e6d9378c": [
      5800
    ],
    "e70e7f7b": [
      7060
    ],
    "ee3edf35": [
      3187
    ],
    "f1e28905": [
      532,
      7220
    ],
    "styles": [
      97,
      179,
      545,
      1108,
      1290,
      1303,
      2529,
      3085,
      3089,
      3208,
      3237,
      3629,
      3751,
      4013,
      4287,
      4368,
      6103,
      7220,
      7361,
      7418,
      7918,
      8493,
      8610,
      9514,
      9817,
      532
    ]
  },
  "assets": {
    "53": {
      "js": [
        {
          "file": "assets/js/935f2afb.7b88784e.js",
          "hash": "21fa2bca068a6293",
          "publicPath": "/dsa/assets/js/935f2afb.7b88784e.js"
        }
      ]
    },
    "75": {
      "js": [
        {
          "file": "assets/js/01ec86e8.59c2a3fd.js",
          "hash": "0604136fdc3faf99",
          "publicPath": "/dsa/assets/js/01ec86e8.59c2a3fd.js"
        }
      ]
    },
    "97": {
      "js": [
        {
          "file": "assets/js/7d087b07.aa1141a9.js",
          "hash": "2d1013d0edea6c7f",
          "publicPath": "/dsa/assets/js/7d087b07.aa1141a9.js"
        }
      ]
    },
    "167": {
      "js": [
        {
          "file": "assets/js/d9d034db.39dd250e.js",
          "hash": "ed212993228a6786",
          "publicPath": "/dsa/assets/js/d9d034db.39dd250e.js"
        }
      ]
    },
    "179": {
      "js": [
        {
          "file": "assets/js/main.d4c8ec31.js",
          "hash": "7daec64d64f4757d",
          "publicPath": "/dsa/assets/js/main.d4c8ec31.js"
        }
      ]
    },
    "532": {
      "css": [
        {
          "file": "assets/css/styles.de1897d8.css",
          "hash": "913e2c0df8695b54",
          "publicPath": "/dsa/assets/css/styles.de1897d8.css"
        }
      ]
    },
    "545": {
      "js": [
        {
          "file": "assets/js/3400adb2.c41efdca.js",
          "hash": "5a452e33bb3e557a",
          "publicPath": "/dsa/assets/js/3400adb2.c41efdca.js"
        }
      ]
    },
    "884": {
      "js": [
        {
          "file": "assets/js/b797b19a.e3888d92.js",
          "hash": "d2061f9bb8b3646a",
          "publicPath": "/dsa/assets/js/b797b19a.e3888d92.js"
        }
      ]
    },
    "1094": {
      "js": [
        {
          "file": "assets/js/e0032ae8.1682baca.js",
          "hash": "11281149d974dd5e",
          "publicPath": "/dsa/assets/js/e0032ae8.1682baca.js"
        }
      ]
    },
    "1108": {
      "js": [
        {
          "file": "assets/js/2b66f623.c213ca9a.js",
          "hash": "0e1b7bf963abdfd2",
          "publicPath": "/dsa/assets/js/2b66f623.c213ca9a.js"
        }
      ]
    },
    "1290": {
      "js": [
        {
          "file": "assets/js/69afaff5.afa678c2.js",
          "hash": "ed05fb41bacddbba",
          "publicPath": "/dsa/assets/js/69afaff5.afa678c2.js"
        }
      ]
    },
    "1303": {
      "js": [
        {
          "file": "assets/js/runtime~main.9174a771.js",
          "hash": "13dc1cd23179885c",
          "publicPath": "/dsa/assets/js/runtime~main.9174a771.js"
        }
      ]
    },
    "1811": {
      "js": [
        {
          "file": "assets/js/878483fc.94a5472c.js",
          "hash": "923d51ce998c45d6",
          "publicPath": "/dsa/assets/js/878483fc.94a5472c.js"
        }
      ]
    },
    "2085": {
      "js": [
        {
          "file": "assets/js/a7ce38cf.066bf6db.js",
          "hash": "b6fc9b024a627c7c",
          "publicPath": "/dsa/assets/js/a7ce38cf.066bf6db.js"
        }
      ]
    },
    "2486": {
      "js": [
        {
          "file": "assets/js/217d5635.532683fc.js",
          "hash": "b4ee1f2fcadef616",
          "publicPath": "/dsa/assets/js/217d5635.532683fc.js"
        }
      ]
    },
    "2529": {
      "js": [
        {
          "file": "assets/js/2529.3bec1a9d.js",
          "hash": "2e4f8e6ec7346816",
          "publicPath": "/dsa/assets/js/2529.3bec1a9d.js"
        }
      ]
    },
    "2535": {
      "js": [
        {
          "file": "assets/js/814f3328.c073c79f.js",
          "hash": "3d4c11cde6d70aa6",
          "publicPath": "/dsa/assets/js/814f3328.c073c79f.js"
        }
      ]
    },
    "2633": {
      "js": [
        {
          "file": "assets/js/92d963c9.15f9c740.js",
          "hash": "f071643f69b628c4",
          "publicPath": "/dsa/assets/js/92d963c9.15f9c740.js"
        }
      ]
    },
    "3085": {
      "js": [
        {
          "file": "assets/js/1f391b9e.a9e9aa32.js",
          "hash": "a42e1c13a19c8790",
          "publicPath": "/dsa/assets/js/1f391b9e.a9e9aa32.js"
        }
      ]
    },
    "3089": {
      "js": [
        {
          "file": "assets/js/a6aa9e1f.01e8f0a8.js",
          "hash": "5c9dfdc5793d0f90",
          "publicPath": "/dsa/assets/js/a6aa9e1f.01e8f0a8.js"
        }
      ]
    },
    "3170": {
      "js": [
        {
          "file": "assets/js/a7e3f0b1.7c6fd50d.js",
          "hash": "a0cddd588d2bdbc0",
          "publicPath": "/dsa/assets/js/a7e3f0b1.7c6fd50d.js"
        }
      ]
    },
    "3187": {
      "js": [
        {
          "file": "assets/js/ee3edf35.d1541ccc.js",
          "hash": "7dafae3cfd3160cd",
          "publicPath": "/dsa/assets/js/ee3edf35.d1541ccc.js"
        }
      ]
    },
    "3208": {
      "js": [
        {
          "file": "assets/js/10f8c402.8ace3538.js",
          "hash": "9bdc4738ef3490ab",
          "publicPath": "/dsa/assets/js/10f8c402.8ace3538.js"
        }
      ]
    },
    "3237": {
      "js": [
        {
          "file": "assets/js/1df93b7f.cf21094a.js",
          "hash": "f015bfc2c335c28d",
          "publicPath": "/dsa/assets/js/1df93b7f.cf21094a.js"
        }
      ]
    },
    "3390": {
      "js": [
        {
          "file": "assets/js/8d8aa384.e31b84ae.js",
          "hash": "f587552e931e3c48",
          "publicPath": "/dsa/assets/js/8d8aa384.e31b84ae.js"
        }
      ]
    },
    "3608": {
      "js": [
        {
          "file": "assets/js/9e4087bc.001784cd.js",
          "hash": "022381f5ea178a0e",
          "publicPath": "/dsa/assets/js/9e4087bc.001784cd.js"
        }
      ]
    },
    "3629": {
      "js": [
        {
          "file": "assets/js/3ae4ab60.9acca18e.js",
          "hash": "1ea6251f78fa9677",
          "publicPath": "/dsa/assets/js/3ae4ab60.9acca18e.js"
        }
      ]
    },
    "3751": {
      "js": [
        {
          "file": "assets/js/3720c009.61f3eb05.js",
          "hash": "1e02ac9cd8d2f850",
          "publicPath": "/dsa/assets/js/3720c009.61f3eb05.js"
        }
      ]
    },
    "4013": {
      "js": [
        {
          "file": "assets/js/01a85c17.b2b2c876.js",
          "hash": "9a8c5339c8a0945f",
          "publicPath": "/dsa/assets/js/01a85c17.b2b2c876.js"
        }
      ]
    },
    "4121": {
      "js": [
        {
          "file": "assets/js/55960ee5.f33ee122.js",
          "hash": "4cabbb66976cf0cc",
          "publicPath": "/dsa/assets/js/55960ee5.f33ee122.js"
        }
      ]
    },
    "4287": {
      "js": [
        {
          "file": "assets/js/15b074d4.77dda56b.js",
          "hash": "c530296ffafdc466",
          "publicPath": "/dsa/assets/js/15b074d4.77dda56b.js"
        }
      ]
    },
    "4368": {
      "js": [
        {
          "file": "assets/js/4368.2c076af9.js",
          "hash": "a84c869354d72aa2",
          "publicPath": "/dsa/assets/js/4368.2c076af9.js"
        }
      ]
    },
    "4605": {
      "js": [
        {
          "file": "assets/js/2af48450.a2177571.js",
          "hash": "00a35b43575d4a57",
          "publicPath": "/dsa/assets/js/2af48450.a2177571.js"
        }
      ]
    },
    "4972": {
      "js": [
        {
          "file": "assets/js/4972.e0a1f0ff.js",
          "hash": "bd0fe8192be395a9",
          "publicPath": "/dsa/assets/js/4972.e0a1f0ff.js"
        },
        {
          "file": "assets/js/1be78505.09b3279a.js",
          "hash": "47165a13afa3b8e0",
          "publicPath": "/dsa/assets/js/1be78505.09b3279a.js"
        }
      ]
    },
    "5522": {
      "js": [
        {
          "file": "assets/js/0a6dc3e9.4ae4a690.js",
          "hash": "61ba859178a82b35",
          "publicPath": "/dsa/assets/js/0a6dc3e9.4ae4a690.js"
        }
      ]
    },
    "5800": {
      "js": [
        {
          "file": "assets/js/e6d9378c.5ce8c5bf.js",
          "hash": "6d29b92dd1d4afe6",
          "publicPath": "/dsa/assets/js/e6d9378c.5ce8c5bf.js"
        }
      ]
    },
    "5942": {
      "js": [
        {
          "file": "assets/js/961b356e.d1a0c85a.js",
          "hash": "e67ce93576bffe61",
          "publicPath": "/dsa/assets/js/961b356e.d1a0c85a.js"
        }
      ]
    },
    "5958": {
      "js": [
        {
          "file": "assets/js/1a118389.845e4556.js",
          "hash": "c770260a26bf8b05",
          "publicPath": "/dsa/assets/js/1a118389.845e4556.js"
        }
      ]
    },
    "6103": {
      "js": [
        {
          "file": "assets/js/ccc49370.3a8c2f0d.js",
          "hash": "c246842847482d87",
          "publicPath": "/dsa/assets/js/ccc49370.3a8c2f0d.js"
        }
      ]
    },
    "6214": {
      "js": [
        {
          "file": "assets/js/60c9bd7f.bba3e5d0.js",
          "hash": "76036e82c7f7f2f0",
          "publicPath": "/dsa/assets/js/60c9bd7f.bba3e5d0.js"
        }
      ]
    },
    "6476": {
      "js": [
        {
          "file": "assets/js/1203df09.4c9eee52.js",
          "hash": "e30306bc449b73c1",
          "publicPath": "/dsa/assets/js/1203df09.4c9eee52.js"
        }
      ]
    },
    "6611": {
      "js": [
        {
          "file": "assets/js/a910c3a6.dda620af.js",
          "hash": "b772dfa4d0cc8fe1",
          "publicPath": "/dsa/assets/js/a910c3a6.dda620af.js"
        }
      ]
    },
    "6737": {
      "js": [
        {
          "file": "assets/js/86ccd6d1.ae5e096f.js",
          "hash": "bbcb609223a54e33",
          "publicPath": "/dsa/assets/js/86ccd6d1.ae5e096f.js"
        }
      ]
    },
    "6743": {
      "js": [
        {
          "file": "assets/js/0fec271b.f0acd2de.js",
          "hash": "5b08f4f24b23a537",
          "publicPath": "/dsa/assets/js/0fec271b.f0acd2de.js"
        }
      ]
    },
    "6828": {
      "js": [
        {
          "file": "assets/js/cd1338b3.7af3061d.js",
          "hash": "576eacc08037fc78",
          "publicPath": "/dsa/assets/js/cd1338b3.7af3061d.js"
        }
      ]
    },
    "7060": {
      "js": [
        {
          "file": "assets/js/e70e7f7b.bbc25738.js",
          "hash": "046eaa12de2c9406",
          "publicPath": "/dsa/assets/js/e70e7f7b.bbc25738.js"
        }
      ]
    },
    "7220": {
      "js": [
        {
          "file": "assets/js/f1e28905.afe2635d.js",
          "hash": "205857ec9667b4f7",
          "publicPath": "/dsa/assets/js/f1e28905.afe2635d.js"
        }
      ]
    },
    "7361": {
      "js": [
        {
          "file": "assets/js/35d10f69.b5739e17.js",
          "hash": "a398a1ab8930c22f",
          "publicPath": "/dsa/assets/js/35d10f69.b5739e17.js"
        }
      ]
    },
    "7412": {
      "js": [
        {
          "file": "assets/js/0fdf012f.56583c70.js",
          "hash": "6ef4d43aca3fe339",
          "publicPath": "/dsa/assets/js/0fdf012f.56583c70.js"
        }
      ]
    },
    "7414": {
      "js": [
        {
          "file": "assets/js/393be207.dc183b12.js",
          "hash": "40e551727debe5d2",
          "publicPath": "/dsa/assets/js/393be207.dc183b12.js"
        }
      ]
    },
    "7418": {
      "js": [
        {
          "file": "assets/js/6bfbe0c6.18feb837.js",
          "hash": "bf97cfc315849677",
          "publicPath": "/dsa/assets/js/6bfbe0c6.18feb837.js"
        }
      ]
    },
    "7773": {
      "js": [
        {
          "file": "assets/js/3fdb0b01.1a8cb43b.js",
          "hash": "d3c5d909ee258a0c",
          "publicPath": "/dsa/assets/js/3fdb0b01.1a8cb43b.js"
        }
      ]
    },
    "7867": {
      "js": [
        {
          "file": "assets/js/96082b4e.8bb7d381.js",
          "hash": "893f85d37930347a",
          "publicPath": "/dsa/assets/js/96082b4e.8bb7d381.js"
        }
      ]
    },
    "7918": {
      "js": [
        {
          "file": "assets/js/17896441.9e670fa3.js",
          "hash": "155ee0afacb8fafa",
          "publicPath": "/dsa/assets/js/17896441.9e670fa3.js"
        }
      ]
    },
    "8493": {
      "js": [
        {
          "file": "assets/js/8fd214de.6ad5cc5e.js",
          "hash": "cc64e132c10343b7",
          "publicPath": "/dsa/assets/js/8fd214de.6ad5cc5e.js"
        }
      ]
    },
    "8610": {
      "js": [
        {
          "file": "assets/js/6875c492.259adf9e.js",
          "hash": "f6ce762e52a32126",
          "publicPath": "/dsa/assets/js/6875c492.259adf9e.js"
        }
      ]
    },
    "8913": {
      "js": [
        {
          "file": "assets/js/92caa433.1e50d43b.js",
          "hash": "94242db779e738ec",
          "publicPath": "/dsa/assets/js/92caa433.1e50d43b.js"
        }
      ]
    },
    "9035": {
      "js": [
        {
          "file": "assets/js/177d2f1b.69d923c4.js",
          "hash": "698d36636d873b7d",
          "publicPath": "/dsa/assets/js/177d2f1b.69d923c4.js"
        }
      ]
    },
    "9053": {
      "js": [
        {
          "file": "assets/js/97580723.78bca23c.js",
          "hash": "cac415fa2d1c0f38",
          "publicPath": "/dsa/assets/js/97580723.78bca23c.js"
        }
      ]
    },
    "9817": {
      "js": [
        {
          "file": "assets/js/14eb3368.29d56338.js",
          "hash": "1e038f1e469a5dc4",
          "publicPath": "/dsa/assets/js/14eb3368.29d56338.js"
        }
      ]
    },
    "9883": {
      "js": [
        {
          "file": "assets/js/34b7720e.201d736f.js",
          "hash": "a8ed7e63fdb811a9",
          "publicPath": "/dsa/assets/js/34b7720e.201d736f.js"
        }
      ]
    },
    "9913": {
      "js": [
        {
          "file": "assets/js/a08e0254.aefa5974.js",
          "hash": "2125332221698101",
          "publicPath": "/dsa/assets/js/a08e0254.aefa5974.js"
        }
      ]
    },
    "9924": {
      "js": [
        {
          "file": "assets/js/df203c0f.9192dc94.js",
          "hash": "7aa595132cf70989",
          "publicPath": "/dsa/assets/js/df203c0f.9192dc94.js"
        }
      ]
    },
    "9971": {
      "js": [
        {
          "file": "assets/js/b53f932d.252e9f83.js",
          "hash": "bd6c8f63bbf897f6",
          "publicPath": "/dsa/assets/js/b53f932d.252e9f83.js"
        }
      ]
    }
  }
}